{
  "algorithm": "concorde_linkern_03_12_19",
  "status": "negative_result_no_strict_improvement",
  "jobs_completed": 250,
  "best_verified_length": 73934,
  "current_upper_bound": 73934,
  "improved_current_upper_bound": false,
  "length_distribution": {
    "73934": 151,
    "73947": 1,
    "73949": 1,
    "73953": 1,
    "73956": 1,
    "73957": 1,
    "73958": 1,
    "73960": 1,
    "73962": 1,
    "73963": 1,
    "73964": 3,
    "73968": 1,
    "73969": 1,
    "73970": 1,
    "73973": 1,
    "73974": 1,
    "73977": 3,
    "73978": 1,
    "73979": 1,
    "73980": 4,
    "73984": 2,
    "73985": 1,
    "73988": 1,
    "73989": 1,
    "73990": 1,
    "73991": 1,
    "73993": 1,
    "73994": 3,
    "73996": 1,
    "73998": 2,
    "73999": 1,
    "74002": 1,
    "74004": 1,
    "74006": 3,
    "74007": 1,
    "74008": 1,
    "74013": 1,
    "74014": 1,
    "74015": 2,
    "74019": 1,
    "74020": 1,
    "74022": 1,
    "74023": 1,
    "74025": 1,
    "74028": 1,
    "74030": 1,
    "74031": 2,
    "74032": 1,
    "74037": 2,
    "74039": 2,
    "74042": 1,
    "74043": 2,
    "74044": 1,
    "74045": 1,
    "74046": 1,
    "74048": 1,
    "74051": 1,
    "74053": 2,
    "74055": 1,
    "74066": 1,
    "74071": 2,
    "74072": 2,
    "74074": 2,
    "74084": 1,
    "74094": 1,
    "74097": 1,
    "74100": 1,
    "74106": 1,
    "74107": 1,
    "74111": 1,
    "74113": 1,
    "74114": 1,
    "74119": 1,
    "74127": 1,
    "74132": 1,
    "74197": 1,
    "74235": 1,
    "74286": 1
  },
  "best_record": {
    "command": "/home/werserk/3-education/hse/combinatorial-optimization/tsp/tools/concorde-build/LINKERN/linkern -Q -s 1 -r 1 -R 1114 -t 20 -h 73933 -y /home/werserk/3-education/hse/combinatorial-optimization/tsp/data/processed/linkern-start-step6-lkh-best.cyc -o /home/werserk/3-education/hse/combinatorial-optimization/tsp/data/processed/linkern-step14-from_lkh_q3-seed-1.cyc /home/werserk/3-education/hse/combinatorial-optimization/tsp/data/processed/challenge-full-matrix.tsp",
    "config_id": "from_lkh_q3",
    "created_at": "2026-06-10T14:14:20.315111+00:00",
    "job_id": "from_lkh_q3__seed_1",
    "log_file": "results/runs/linkern-step14-from_lkh_q3-seed-1.log",
    "output_cycle_file": "data/processed/linkern-step14-from_lkh_q3-seed-1.cyc",
    "parameters": {
      "args": [],
      "run_kicks": 1114,
      "time_bound_seconds": 20,
      "use_lkh_start": true
    },
    "runtime_seconds": 0.66041,
    "seed": 1,
    "solver_length": 73934,
    "status": "done",
    "verified_length": 73934
  },
  "lower_bound": 65493.4373688764,
  "absolute_gap_at_best": 8440.562631123597,
  "relative_gap_to_lower_at_best": 0.1288764641193607,
  "progress_ledger": "results/runs/step14-linkern-progress.jsonl",
  "run_artifact": "results/runs/step14-linkern-wave.json",
  "log": "results/runs/step14-linkern-wave.log",
  "build_log": "results/runs/concorde-build-full-2.log",
  "created_at": "2026-06-10T14:20:52.007616+00:00"
}
